odoo/addons/hr_employee_document_from_applicant/README.rst
odoo/addons/hr_employee_document_from_applicant/__init__.py
odoo/addons/hr_employee_document_from_applicant/__manifest__.py
odoo/addons/hr_employee_document_from_applicant/i18n/es_MX.po
odoo/addons/hr_employee_document_from_applicant/i18n/hr_employee_document_from_applicant.pot
odoo/addons/hr_employee_document_from_applicant/i18n/it.po
odoo/addons/hr_employee_document_from_applicant/models/__init__.py
odoo/addons/hr_employee_document_from_applicant/models/hr_employee.py
odoo/addons/hr_employee_document_from_applicant/readme/CONTRIBUTORS.rst
odoo/addons/hr_employee_document_from_applicant/readme/DESCRIPTION.rst
odoo/addons/hr_employee_document_from_applicant/readme/USAGE.rst
odoo/addons/hr_employee_document_from_applicant/static/description/icon.png
odoo/addons/hr_employee_document_from_applicant/static/description/index.html
odoo_addon_hr_employee_document_from_applicant-16.0.1.0.0.5.dist-info/METADATA
odoo_addon_hr_employee_document_from_applicant-16.0.1.0.0.5.dist-info/WHEEL
odoo_addon_hr_employee_document_from_applicant-16.0.1.0.0.5.dist-info/top_level.txt
odoo_addon_hr_employee_document_from_applicant-16.0.1.0.0.5.dist-info/RECORD
