Metadata-Version: 2.1
Name: odoo-addon-hr_employee_document_from_applicant
Version: 16.0.1.0.0.5
Summary: HR Employee Document from Applicant
Home-page: https://github.com/OCA/hr
Author: Odoo Community Association (OCA), Open Source Integrators
Author-email: support@odoo-community.org
License: AGPL-3
Classifier: Programming Language :: Python
Classifier: Framework :: Odoo
Classifier: Framework :: Odoo :: 16.0
Classifier: License :: OSI Approved :: GNU Affero General Public License v3
Requires-Python: >=3.10
Requires-Dist: odoo-addon-hr-employee-document<16.1dev,>=16.0dev
Requires-Dist: odoo<16.1dev,>=16.0a
